qufe/__init__.py
qufe/base.py
qufe/dbhandler.py
qufe/excludebracket.py
qufe/filehandler.py
qufe/interactionhandler.py
qufe/pdhandler.py
qufe/texthandler.py
qufe/wbhandler.py
qufe-0.5.16.dist-info/METADATA
qufe-0.5.16.dist-info/WHEEL
qufe-0.5.16.dist-info/top_level.txt
qufe-0.5.16.dist-info/RECORD
