Metadata-Version: 2.4
Name: qufe
Version: 0.5.16
Summary: A comprehensive Python utility library for data processing, file handling, database management, and automation tasks
Author-email: Bongtae Jeon <bongtae.jeon@gmail.com>
Maintainer-email: Bongtae Jeon <bongtae.jeon@gmail.com>
License: MIT
Project-URL: Homepage, https://dev.qufe.net/
Project-URL: Repository, https://github.com/qufe/qufe
Project-URL: Documentation, https://qufe.readthedocs.io
Project-URL: Bug Tracker, https://github.com/qufe/qufe/issues
Keywords: utilities,automation,data-processing,database,file-handling,web-scraping,image-processing
Classifier: Development Status :: 4 - Beta
Classifier: Intended Audience :: Developers
Classifier: License :: OSI Approved :: MIT License
Classifier: Operating System :: OS Independent
Classifier: Programming Language :: Python :: 3
Classifier: Programming Language :: Python :: 3.10
Classifier: Programming Language :: Python :: 3.11
Classifier: Programming Language :: Python :: 3.12
Classifier: Programming Language :: Python :: 3.13
Classifier: Topic :: Software Development :: Libraries :: Python Modules
Classifier: Topic :: Utilities
Classifier: Topic :: Database
Classifier: Topic :: Text Processing
Classifier: Topic :: System :: Filesystems
Requires-Python: >=3.8
Provides-Extra: database
Requires-Dist: sqlalchemy>=1.3.0; extra == "database"
Requires-Dist: python-dotenv>=0.15.0; extra == "database"
Provides-Extra: data
Requires-Dist: pandas>=1.1.0; extra == "data"
Requires-Dist: numpy>=1.17.0; extra == "data"
Provides-Extra: web
Requires-Dist: selenium>=3.141.0; extra == "web"
Provides-Extra: vision
Requires-Dist: opencv-python>=4.1.0; extra == "vision"
Requires-Dist: matplotlib>=3.1.0; extra == "vision"
Requires-Dist: pyautogui>=0.9.48; extra == "vision"
Requires-Dist: mss>=4.0.0; extra == "vision"
Provides-Extra: jupyter
Requires-Dist: ipython>=6.0.0; extra == "jupyter"
Provides-Extra: all
Requires-Dist: sqlalchemy>=1.3.0; extra == "all"
Requires-Dist: python-dotenv>=0.15.0; extra == "all"
Requires-Dist: pandas>=1.1.0; extra == "all"
Requires-Dist: numpy>=1.17.0; extra == "all"
Requires-Dist: selenium>=4.0.0; extra == "all"
Requires-Dist: opencv-python>=4.1.0; extra == "all"
Requires-Dist: matplotlib>=3.1.0; extra == "all"
Requires-Dist: pyautogui>=0.9.48; extra == "all"
Requires-Dist: mss>=4.0.0; extra == "all"
Requires-Dist: ipython>=6.0.0; extra == "all"
Provides-Extra: dev
Requires-Dist: pytest>=6.0; extra == "dev"
Requires-Dist: pytest-cov; extra == "dev"
Requires-Dist: black; extra == "dev"
Requires-Dist: flake8; extra == "dev"
Requires-Dist: mypy; extra == "dev"
Requires-Dist: pre-commit; extra == "dev"
Provides-Extra: docs
Requires-Dist: sphinx>=7.0.0; extra == "docs"
Requires-Dist: sphinx-rtd-theme>=2.0.0; extra == "docs"
Requires-Dist: sphinx-autodoc-typehints>=1.24.0; extra == "docs"
